invest_calc/__init__.py
invest_calc/fin_calc.py
sales_report/__init__.py
sales_report/sales_report.py
transaction_report/__init__.py
transaction_report/transaction_report.py
transaction_report-0.1.0.dist-info/METADATA
transaction_report-0.1.0.dist-info/WHEEL
transaction_report-0.1.0.dist-info/top_level.txt
transaction_report-0.1.0.dist-info/RECORD
